setup.py
client/__init__.py
client/client.py
client/client/__init__.py
client/client/add_contact.py
client/client/client_db.py
client/client/del_contact.py
client/client/main_window.py
client/client/main_window_conv.py
client/client/start_dialog.py
client/client/transport.py
client/common/__init__.py
client/common/decos.py
client/common/descrptrs.py
client/common/errors.py
client/common/metaclasses.py
client/common/utils.py
client/common/variables.py
client/unit_tests/__init__.py
client/unit_tests/test_client.py
client/unit_tests/test_server.py
client/unit_tests/test_utils.py
mess_client_january.egg-info/PKG-INFO
mess_client_january.egg-info/SOURCES.txt
mess_client_january.egg-info/dependency_links.txt
mess_client_january.egg-info/requires.txt
mess_client_january.egg-info/top_level.txt